MANIFEST.in
README.md
setup.py
pysipgate/__init__.py
pysipgate/gui.py
pysipgate/main.py
pysipgate/sipgate.py
pysipgate.egg-info/PKG-INFO
pysipgate.egg-info/SOURCES.txt
pysipgate.egg-info/dependency_links.txt
pysipgate.egg-info/entry_points.txt
pysipgate.egg-info/top_level.txt