Metadata-Version: 1.1
Name: pysipgate
Version: 0.1.2
Summary: Client for the Sipgate API
Home-page: https://github.com/thammi/pysipgate
Author: Thammi
Author-email: thammi@chaossource.net
License: GPLv3
Keywords: sipgate
Platform: UNKNOWN
Classifier: Programming Language :: Python :: 3
Classifier: Development Status :: 4 - Beta
Classifier: Environment :: X11 Applications :: Qt
Classifier: Intended Audience :: End Users/Desktop
Classifier: License :: OSI Approved :: GNU General Public License v3 (GPLv3)
Classifier: Natural Language :: English
Classifier: Topic :: Communications :: Telephony
